pymlogic/__init__.py
pymlogic/blocks.py
pymlogic/draw_call.py
pymlogic/environment.py
pymlogic/instructions.py
pymlogic/interpreter.py
pymlogic/parser.py
pymlogic/sensable.py
pymlogic/variables.py
pymlogic-0.0.3.dist-info/METADATA
pymlogic-0.0.3.dist-info/WHEEL
pymlogic-0.0.3.dist-info/licenses/LICENSE
pymlogic-0.0.3.dist-info/RECORD
