Metadata-Version: 2.3
Name: pymlogic
Version: 0.0.3
Summary: A package for executing mindustry logic (mlog) code
Author: skyethefoxyfox
Classifier: License :: OSI Approved :: MIT License
Classifier: Operating System :: OS Independent
Classifier: Programming Language :: Python :: 3
Requires-Python: >=3.12
